helloaaz/__init__.py
helloaaz/main.py
helloaaz-0.1.0.dist-info/WHEEL
helloaaz-0.1.0.dist-info/METADATA
helloaaz-0.1.0.dist-info/RECORD
