Metadata-Version: 2.1
Name: helloaaz
Version: 0.1.0
Summary: 
Author: jdan98
Author-email: 57507030+jdan98@users.noreply.github.com
Requires-Python: >=3.9,<4.0
Classifier: Programming Language :: Python :: 3
Classifier: Programming Language :: Python :: 3.9
Requires-Dist: pyfiglet (>=0.8.post1,<0.9)
Requires-Dist: termcolor (>=1.1.0,<2.0.0)
